wag_advanced_analytics_utils/__init__.py
wag_advanced_analytics_utils/athena_data_provider.py
wag_advanced_analytics_utils/logger.py
wag_advanced_analytics_utils/metrics.py
wag_advanced_analytics_utils/s3_client.py
wag_advanced_analytics_utils-0.0.5.dist-info/METADATA
wag_advanced_analytics_utils-0.0.5.dist-info/WHEEL
wag_advanced_analytics_utils-0.0.5.dist-info/licenses/LICENSE
wag_advanced_analytics_utils-0.0.5.dist-info/RECORD
