Metadata-Version: 2.1
Name: wag_advanced_analytics_utils
Version: 0.0.5
Summary: Package containing the common functions used in all the Advanced Analytics algorithms
Project-URL: Homepage, https://github.com/
Author-email: BGR <bgr@whiteawaygroup.com>
License-File: LICENSE
Classifier: License :: OSI Approved :: MIT License
Classifier: Operating System :: OS Independent
Classifier: Programming Language :: Python :: 3
Requires-Python: >=3.9
